prebuilt_RAG_LU/__init__.py
prebuilt_RAG_LU/config.py
prebuilt_RAG_LU/embedding_generator.py
prebuilt_RAG_LU/llm_generator.py
prebuilt_RAG_LU/vector_database.py
prebuilt_RAG_LU-1.0.4.dist-info/LICENSE
prebuilt_RAG_LU-1.0.4.dist-info/METADATA
prebuilt_RAG_LU-1.0.4.dist-info/WHEEL
prebuilt_RAG_LU-1.0.4.dist-info/top_level.txt
prebuilt_RAG_LU-1.0.4.dist-info/RECORD
